<?xml version="1.0" encoding="UTF-8"?>

<!DOCTYPE struts PUBLIC
        "-//Apache Software Foundation//DTD Struts Configuration 2.3//EN"
        "http://struts.apache.org/dtds/struts-2.3.dtd">

<struts>
    <package name="gii-json-default" namespace="/" extends="json-default">
        <action name="schema" class="org.mybatis.gii.action.SchemaAction">
            <result type="json">
                <param name="root">allowedTableNames</param>
            </result>
        </action>
    </package>
</struts>
